dig_ana_sim_out/digital/design.v
// ============================================================
// hc595.v — behavioral model of the 74HC595 8-bit serial-in,
// serial/parallel-out shift register with output latch.
//
// Port names match the KiCad 74xx:74HC595 pin functions so the
// structural netlist builder can wire by pinfunction:
//   SER    pin 14  serial data in
//   SRCLK  pin 11  shift-register clock (rising edge)
//   RCLK   pin 12  storage/latch clock (rising edge)
//   SRCLR_n pin 10 async shift-register clear, active low
//   OE_n   pin 13  output enable, active low (tri-states QA..QH)
//   QA..QH pins 15,1..7  parallel outputs
//   QH_s   pin 9   serial out (QH' — for daisy-chaining)
//
// Chaining: connect one stage's QH_s to the next stage's SER.
// ============================================================
`timescale 1ns/1ps
module hc595 (
    input  wire SER,
    input  wire SRCLK,
    input  wire RCLK,
    input  wire SRCLR_n,
    input  wire OE_n,
    output wire QA, QB, QC, QD, QE, QF, QG, QH,
    output wire QH_s
);
    reg [7:0] shift;   // shift register
    reg [7:0] latch;   // storage register

    // Shift register: sample SER on rising SRCLK; async clear.
    always @(posedge SRCLK or negedge SRCLR_n) begin
        if (!SRCLR_n)
            shift <= 8'b0;
        else
            shift <= {shift[6:0], SER};
    end

    // Storage register latches the shift register on rising RCLK.
    always @(posedge RCLK)
        latch <= shift;

    // Parallel outputs, tri-stated when OE_n is high.
    assign {QH, QG, QF, QE, QD, QC, QB, QA} = OE_n ? 8'bz : latch;

    // Serial output is the MSB of the shift register (daisy-chain).
    assign QH_s = shift[7];
endmodule


module analog_NN_digital (
    input  RCLK,
    input  SRCLK,
    input  ser,
    output CS11,
    output CS11_h,
    output CS11_neg,
    output CS11_neg_h,
    output CS12,
    output CS12_h,
    output CS12_neg,
    output CS12_neg_h,
    output CS13,
    output CS13_h,
    output CS13_neg,
    output CS13_neg_h,
    output CS14_h,
    output CS14_neg_h,
    output CS21,
    output CS21_h,
    output CS21_neg,
    output CS21_neg_h,
    output CS22,
    output CS22_h,
    output CS22_neg,
    output CS22_neg_h,
    output CS23,
    output CS23_h,
    output CS23_neg,
    output CS23_neg_h,
    output CS24_h,
    output CS24_neg_h,
    output CS31,
    output CS31_h,
    output CS31_neg,
    output CS31_neg_h,
    output CS32,
    output CS32_h,
    output CS32_neg,
    output CS32_neg_h,
    output CS33,
    output CS33_h,
    output CS33_neg,
    output CS33_neg_h,
    output CS34_h,
    output CS34_neg_h,
    output CS41,
    output CS41_h,
    output CS41_neg,
    output CS41_neg_h,
    output CS42,
    output CS42_h,
    output CS42_neg,
    output CS42_neg_h,
    output CS43,
    output CS43_h,
    output CS43_neg,
    output CS43_neg_h,
    output CS44_h,
    output CS44_neg_h,
    output Wo1,
    output Wo1_neg,
    output Wo2,
    output Wo2_neg,
    output Wo3,
    output Wo3_neg,
    output Wo4,
    output Wo4_neg,
    output unconnected__U39_QH__Pad9_
);
    wire GND = 1'b0;
    wire VCC = 1'b1;
    wire Net__U36_QH__;
    wire Net__U36_SER_;
    wire Net__U37_QH__;
    wire Net__U38_QH__;
    wire Net__U93_QH__;
    wire Net__U94_QH__;
    wire Net__U95_QH__;

    hc595 U36 ( .SER(Net__U36_SER_), .SRCLK(SRCLK), .RCLK(RCLK), .SRCLR_n(VCC), .OE_n(GND), .QA(CS11_neg), .QB(CS21_neg), .QC(CS31_neg), .QD(CS41_neg), .QE(CS12_neg), .QF(CS22_neg), .QG(CS32_neg), .QH(CS42_neg), .QH_s(Net__U36_QH__) );
    hc595 U37 ( .SER(Net__U36_QH__), .SRCLK(SRCLK), .RCLK(RCLK), .SRCLR_n(VCC), .OE_n(GND), .QA(CS13_neg), .QB(CS23_neg), .QC(CS33_neg), .QD(CS43_neg), .QE(CS11_neg_h), .QF(CS21_neg_h), .QG(CS31_neg_h), .QH(CS41_neg_h), .QH_s(Net__U37_QH__) );
    hc595 U38 ( .SER(Net__U37_QH__), .SRCLK(SRCLK), .RCLK(RCLK), .SRCLR_n(VCC), .OE_n(GND), .QA(CS12_neg_h), .QB(CS22_neg_h), .QC(CS32_neg_h), .QD(CS42_neg_h), .QE(CS13_neg_h), .QF(CS23_neg_h), .QG(CS33_neg_h), .QH(CS43_neg_h), .QH_s(Net__U38_QH__) );
    hc595 U39 ( .SER(Net__U38_QH__), .SRCLK(SRCLK), .RCLK(RCLK), .SRCLR_n(VCC), .OE_n(GND), .QA(CS14_neg_h), .QB(CS24_neg_h), .QC(CS34_neg_h), .QD(CS44_neg_h), .QE(Wo1_neg), .QF(Wo2_neg), .QG(Wo3_neg), .QH(Wo4_neg), .QH_s(unconnected__U39_QH__Pad9_) );
    hc595 U93 ( .SER(ser), .SRCLK(SRCLK), .RCLK(RCLK), .SRCLR_n(VCC), .OE_n(GND), .QA(CS11), .QB(CS21), .QC(CS31), .QD(CS41), .QE(CS12), .QF(CS22), .QG(CS32), .QH(CS42), .QH_s(Net__U93_QH__) );
    hc595 U94 ( .SER(Net__U93_QH__), .SRCLK(SRCLK), .RCLK(RCLK), .SRCLR_n(VCC), .OE_n(GND), .QA(CS13), .QB(CS23), .QC(CS33), .QD(CS43), .QE(CS11_h), .QF(CS21_h), .QG(CS31_h), .QH(CS41_h), .QH_s(Net__U94_QH__) );
    hc595 U95 ( .SER(Net__U94_QH__), .SRCLK(SRCLK), .RCLK(RCLK), .SRCLR_n(VCC), .OE_n(GND), .QA(CS12_h), .QB(CS22_h), .QC(CS32_h), .QD(CS42_h), .QE(CS13_h), .QF(CS23_h), .QG(CS33_h), .QH(CS43_h), .QH_s(Net__U95_QH__) );
    hc595 U96 ( .SER(Net__U95_QH__), .SRCLK(SRCLK), .RCLK(RCLK), .SRCLR_n(VCC), .OE_n(GND), .QA(CS14_h), .QB(CS24_h), .QC(CS34_h), .QD(CS44_h), .QE(Wo1), .QF(Wo2), .QG(Wo3), .QH(Wo4), .QH_s(Net__U36_SER_) );
endmodule // analog_NN_digital

dig_ana_sim_out/digital/tb.v
`timescale 1ns/1ps
module tb;
    reg RCLK = 1'b0;
    reg SRCLK = 1'b0;
    reg ser = 1'b0;
    wire CS11;
    wire CS11_h;
    wire CS11_neg;
    wire CS11_neg_h;
    wire CS12;
    wire CS12_h;
    wire CS12_neg;
    wire CS12_neg_h;
    wire CS13;
    wire CS13_h;
    wire CS13_neg;
    wire CS13_neg_h;
    wire CS14_h;
    wire CS14_neg_h;
    wire CS21;
    wire CS21_h;
    wire CS21_neg;
    wire CS21_neg_h;
    wire CS22;
    wire CS22_h;
    wire CS22_neg;
    wire CS22_neg_h;
    wire CS23;
    wire CS23_h;
    wire CS23_neg;
    wire CS23_neg_h;
    wire CS24_h;
    wire CS24_neg_h;
    wire CS31;
    wire CS31_h;
    wire CS31_neg;
    wire CS31_neg_h;
    wire CS32;
    wire CS32_h;
    wire CS32_neg;
    wire CS32_neg_h;
    wire CS33;
    wire CS33_h;
    wire CS33_neg;
    wire CS33_neg_h;
    wire CS34_h;
    wire CS34_neg_h;
    wire CS41;
    wire CS41_h;
    wire CS41_neg;
    wire CS41_neg_h;
    wire CS42;
    wire CS42_h;
    wire CS42_neg;
    wire CS42_neg_h;
    wire CS43;
    wire CS43_h;
    wire CS43_neg;
    wire CS43_neg_h;
    wire CS44_h;
    wire CS44_neg_h;
    wire Wo1;
    wire Wo1_neg;
    wire Wo2;
    wire Wo2_neg;
    wire Wo3;
    wire Wo3_neg;
    wire Wo4;
    wire Wo4_neg;
    wire unconnected__U39_QH__Pad9_;
    analog_NN_digital dut ( .RCLK(RCLK), .SRCLK(SRCLK), .ser(ser), .CS11(CS11), .CS11_h(CS11_h), .CS11_neg(CS11_neg), .CS11_neg_h(CS11_neg_h), .CS12(CS12), .CS12_h(CS12_h), .CS12_neg(CS12_neg), .CS12_neg_h(CS12_neg_h), .CS13(CS13), .CS13_h(CS13_h), .CS13_neg(CS13_neg), .CS13_neg_h(CS13_neg_h), .CS14_h(CS14_h), .CS14_neg_h(CS14_neg_h), .CS21(CS21), .CS21_h(CS21_h), .CS21_neg(CS21_neg), .CS21_neg_h(CS21_neg_h), .CS22(CS22), .CS22_h(CS22_h), .CS22_neg(CS22_neg), .CS22_neg_h(CS22_neg_h), .CS23(CS23), .CS23_h(CS23_h), .CS23_neg(CS23_neg), .CS23_neg_h(CS23_neg_h), .CS24_h(CS24_h), .CS24_neg_h(CS24_neg_h), .CS31(CS31), .CS31_h(CS31_h), .CS31_neg(CS31_neg), .CS31_neg_h(CS31_neg_h), .CS32(CS32), .CS32_h(CS32_h), .CS32_neg(CS32_neg), .CS32_neg_h(CS32_neg_h), .CS33(CS33), .CS33_h(CS33_h), .CS33_neg(CS33_neg), .CS33_neg_h(CS33_neg_h), .CS34_h(CS34_h), .CS34_neg_h(CS34_neg_h), .CS41(CS41), .CS41_h(CS41_h), .CS41_neg(CS41_neg), .CS41_neg_h(CS41_neg_h), .CS42(CS42), .CS42_h(CS42_h), .CS42_neg(CS42_neg), .CS42_neg_h(CS42_neg_h), .CS43(CS43), .CS43_h(CS43_h), .CS43_neg(CS43_neg), .CS43_neg_h(CS43_neg_h), .CS44_h(CS44_h), .CS44_neg_h(CS44_neg_h), .Wo1(Wo1), .Wo1_neg(Wo1_neg), .Wo2(Wo2), .Wo2_neg(Wo2_neg), .Wo3(Wo3), .Wo3_neg(Wo3_neg), .Wo4(Wo4), .Wo4_neg(Wo4_neg), .unconnected__U39_QH__Pad9_(unconnected__U39_QH__Pad9_) );
    integer fd, code, i, dt;
    reg [8*32:1] line;
    initial begin
        $dumpfile("dump.vcd");
        $dumpvars(0, tb);
        fd = $fopen("stim.txt", "r");
        if (fd == 0) begin $finish; end
        while (!$feof(fd)) begin
            code = $fscanf(fd, "%d", dt);
            if (code != 1) begin i = $fgetc(fd); end
            code = $fscanf(fd, "%d", RCLK);
            code = $fscanf(fd, "%d", SRCLK);
            code = $fscanf(fd, "%d", ser);
            #(dt);
        end
        $fclose(fd);
        #1 $finish;
    end
endmodule

dig_ana_sim_out/digital/dump.vcd
$date
	Fri Jul 17 06:20:20 2026
$end
$version
	Icarus Verilog
$end
$timescale
	1ps
$end
$scope module tb $end
$var wire 1 ! unconnected__U39_QH__Pad9_ $end
$var wire 1 " Wo4_neg $end
$var wire 1 # Wo4 $end
$var wire 1 $ Wo3_neg $end
$var wire 1 % Wo3 $end
$var wire 1 & Wo2_neg $end
$var wire 1 ' Wo2 $end
$var wire 1 ( Wo1_neg $end
$var wire 1 ) Wo1 $end
$var wire 1 * CS44_neg_h $end
$var wire 1 + CS44_h $end
$var wire 1 , CS43_neg_h $end
$var wire 1 - CS43_neg $end
$var wire 1 . CS43_h $end
$var wire 1 / CS43 $end
$var wire 1 0 CS42_neg_h $end
$var wire 1 1 CS42_neg $end
$var wire 1 2 CS42_h $end
$var wire 1 3 CS42 $end
$var wire 1 4 CS41_neg_h $end
$var wire 1 5 CS41_neg $end
$var wire 1 6 CS41_h $end
$var wire 1 7 CS41 $end
$var wire 1 8 CS34_neg_h $end
$var wire 1 9 CS34_h $end
$var wire 1 : CS33_neg_h $end
$var wire 1 ; CS33_neg $end
$var wire 1 < CS33_h $end
$var wire 1 = CS33 $end
$var wire 1 > CS32_neg_h $end
$var wire 1 ? CS32_neg $end
$var wire 1 @ CS32_h $end
$var wire 1 A CS32 $end
$var wire 1 B CS31_neg_h $end
$var wire 1 C CS31_neg $end
$var wire 1 D CS31_h $end
$var wire 1 E CS31 $end
$var wire 1 F CS24_neg_h $end
$var wire 1 G CS24_h $end
$var wire 1 H CS23_neg_h $end
$var wire 1 I CS23_neg $end
$var wire 1 J CS23_h $end
$var wire 1 K CS23 $end
$var wire 1 L CS22_neg_h $end
$var wire 1 M CS22_neg $end
$var wire 1 N CS22_h $end
$var wire 1 O CS22 $end
$var wire 1 P CS21_neg_h $end
$var wire 1 Q CS21_neg $end
$var wire 1 R CS21_h $end
$var wire 1 S CS21 $end
$var wire 1 T CS14_neg_h $end
$var wire 1 U CS14_h $end
$var wire 1 V CS13_neg_h $end
$var wire 1 W CS13_neg $end
$var wire 1 X CS13_h $end
$var wire 1 Y CS13 $end
$var wire 1 Z CS12_neg_h $end
$var wire 1 [ CS12_neg $end
$var wire 1 \ CS12_h $end
$var wire 1 ] CS12 $end
$var wire 1 ^ CS11_neg_h $end
$var wire 1 _ CS11_neg $end
$var wire 1 ` CS11_h $end
$var wire 1 a CS11 $end
$var reg 1 b RCLK $end
$var reg 1 c SRCLK $end
$var reg 1 d ser $end
$var integer 32 e code [31:0] $end
$var integer 32 f dt [31:0] $end
$var integer 32 g fd [31:0] $end
$var integer 32 h i [31:0] $end
$scope module dut $end
$var wire 1 i GND $end
$var wire 1 b RCLK $end
$var wire 1 c SRCLK $end
$var wire 1 j VCC $end
$var wire 1 d ser $end
$var wire 1 ! unconnected__U39_QH__Pad9_ $end
$var wire 1 " Wo4_neg $end
$var wire 1 # Wo4 $end
$var wire 1 $ Wo3_neg $end
$var wire 1 % Wo3 $end
$var wire 1 & Wo2_neg $end
$var wire 1 ' Wo2 $end
$var wire 1 ( Wo1_neg $end
$var wire 1 ) Wo1 $end
$var wire 1 k Net__U95_QH__ $end
$var wire 1 l Net__U94_QH__ $end
$var wire 1 m Net__U93_QH__ $end
$var wire 1 n Net__U38_QH__ $end
$var wire 1 o Net__U37_QH__ $end
$var wire 1 p Net__U36_SER_ $end
$var wire 1 q Net__U36_QH__ $end
$var wire 1 * CS44_neg_h $end
$var wire 1 + CS44_h $end
$var wire 1 , CS43_neg_h $end
$var wire 1 - CS43_neg $end
$var wire 1 . CS43_h $end
$var wire 1 / CS43 $end
$var wire 1 0 CS42_neg_h $end
$var wire 1 1 CS42_neg $end
$var wire 1 2 CS42_h $end
$var wire 1 3 CS42 $end
$var wire 1 4 CS41_neg_h $end
$var wire 1 5 CS41_neg $end
$var wire 1 6 CS41_h $end
$var wire 1 7 CS41 $end
$var wire 1 8 CS34_neg_h $end
$var wire 1 9 CS34_h $end
$var wire 1 : CS33_neg_h $end
$var wire 1 ; CS33_neg $end
$var wire 1 < CS33_h $end
$var wire 1 = CS33 $end
$var wire 1 > CS32_neg_h $end
$var wire 1 ? CS32_neg $end
$var wire 1 @ CS32_h $end
$var wire 1 A CS32 $end
$var wire 1 B CS31_neg_h $end
$var wire 1 C CS31_neg $end
$var wire 1 D CS31_h $end
$var wire 1 E CS31 $end
$var wire 1 F CS24_neg_h $end
$var wire 1 G CS24_h $end
$var wire 1 H CS23_neg_h $end
$var wire 1 I CS23_neg $end
$var wire 1 J CS23_h $end
$var wire 1 K CS23 $end
$var wire 1 L CS22_neg_h $end
$var wire 1 M CS22_neg $end
$var wire 1 N CS22_h $end
$var wire 1 O CS22 $end
$var wire 1 P CS21_neg_h $end
$var wire 1 Q CS21_neg $end
$var wire 1 R CS21_h $end
$var wire 1 S CS21 $end
$var wire 1 T CS14_neg_h $end
$var wire 1 U CS14_h $end
$var wire 1 V CS13_neg_h $end
$var wire 1 W CS13_neg $end
$var wire 1 X CS13_h $end
$var wire 1 Y CS13 $end
$var wire 1 Z CS12_neg_h $end
$var wire 1 [ CS12_neg $end
$var wire 1 \ CS12_h $end
$var wire 1 ] CS12 $end
$var wire 1 ^ CS11_neg_h $end
$var wire 1 _ CS11_neg $end
$var wire 1 ` CS11_h $end
$var wire 1 a CS11 $end
$scope module U36 $end
$var wire 1 i OE_n $end
$var wire 1 b RCLK $end
$var wire 1 c SRCLK $end
$var wire 1 j SRCLR_n $end
$var wire 1 p SER $end
$var wire 1 q QH_s $end
$var wire 1 1 QH $end
$var wire 1 ? QG $end
$var wire 1 M QF $end
$var wire 1 [ QE $end
$var wire 1 5 QD $end
$var wire 1 C QC $end
$var wire 1 Q QB $end
$var wire 1 _ QA $end
$var reg 8 r latch [7:0] $end
$var reg 8 s shift [7:0] $end
$upscope $end
$scope module U37 $end
$var wire 1 i OE_n $end
$var wire 1 b RCLK $end
$var wire 1 q SER $end
$var wire 1 c SRCLK $end
$var wire 1 j SRCLR_n $end
$var wire 1 o QH_s $end
$var wire 1 4 QH $end
$var wire 1 B QG $end
$var wire 1 P QF $end
$var wire 1 ^ QE $end
$var wire 1 - QD $end
$var wire 1 ; QC $end
$var wire 1 I QB $end
$var wire 1 W QA $end
$var reg 8 t latch [7:0] $end
$var reg 8 u shift [7:0] $end
$upscope $end
$scope module U38 $end
$var wire 1 i OE_n $end
$var wire 1 b RCLK $end
$var wire 1 o SER $end
$var wire 1 c SRCLK $end
$var wire 1 j SRCLR_n $end
$var wire 1 n QH_s $end
$var wire 1 , QH $end
$var wire 1 : QG $end
$var wire 1 H QF $end
$var wire 1 V QE $end
$var wire 1 0 QD $end
$var wire 1 > QC $end
$var wire 1 L QB $end
$var wire 1 Z QA $end
$var reg 8 v latch [7:0] $end
$var reg 8 w shift [7:0] $end
$upscope $end
$scope module U39 $end
$var wire 1 i OE_n $end
$var wire 1 b RCLK $end
$var wire 1 n SER $end
$var wire 1 c SRCLK $end
$var wire 1 j SRCLR_n $end
$var wire 1 ! QH_s $end
$var wire 1 " QH $end
$var wire 1 $ QG $end
$var wire 1 & QF $end
$var wire 1 ( QE $end
$var wire 1 * QD $end
$var wire 1 8 QC $end
$var wire 1 F QB $end
$var wire 1 T QA $end
$var reg 8 x latch [7:0] $end
$var reg 8 y shift [7:0] $end
$upscope $end
$scope module U93 $end
$var wire 1 i OE_n $end
$var wire 1 b RCLK $end
$var wire 1 d SER $end
$var wire 1 c SRCLK $end
$var wire 1 j SRCLR_n $end
$var wire 1 m QH_s $end
$var wire 1 3 QH $end
$var wire 1 A QG $end
$var wire 1 O QF $end
$var wire 1 ] QE $end
$var wire 1 7 QD $end
$var wire 1 E QC $end
$var wire 1 S QB $end
$var wire 1 a QA $end
$var reg 8 z latch [7:0] $end
$var reg 8 { shift [7:0] $end
$upscope $end
$scope module U94 $end
$var wire 1 i OE_n $end
$var wire 1 b RCLK $end
$var wire 1 m SER $end
$var wire 1 c SRCLK $end
$var wire 1 j SRCLR_n $end
$var wire 1 l QH_s $end
$var wire 1 6 QH $end
$var wire 1 D QG $end
$var wire 1 R QF $end
$var wire 1 ` QE $end
$var wire 1 / QD $end
$var wire 1 = QC $end
$var wire 1 K QB $end
$var wire 1 Y QA $end
$var reg 8 | latch [7:0] $end
$var reg 8 } shift [7:0] $end
$upscope $end
$scope module U95 $end
$var wire 1 i OE_n $end
$var wire 1 b RCLK $end
$var wire 1 l SER $end
$var wire 1 c SRCLK $end
$var wire 1 j SRCLR_n $end
$var wire 1 k QH_s $end
$var wire 1 . QH $end
$var wire 1 < QG $end
$var wire 1 J QF $end
$var wire 1 X QE $end
$var wire 1 2 QD $end
$var wire 1 @ QC $end
$var wire 1 N QB $end
$var wire 1 \ QA $end
$var reg 8 ~ latch [7:0] $end
$var reg 8 !" shift [7:0] $end
$upscope $end
$scope module U96 $end
$var wire 1 i OE_n $end
$var wire 1 b RCLK $end
$var wire 1 k SER $end
$var wire 1 c SRCLK $end
$var wire 1 j SRCLR_n $end
$var wire 1 p QH_s $end
$var wire 1 # QH $end
$var wire 1 % QG $end
$var wire 1 ' QF $end
$var wire 1 ) QE $end
$var wire 1 + QD $end
$var wire 1 9 QC $end
$var wire 1 G QB $end
$var wire 1 U QA $end
$var reg 8 "" latch [7:0] $end
$var reg 8 #" shift [7:0] $end
$upscope $end
$upscope $end
$upscope $end
$enddefinitions $end
$comment Show the parameter values. $end
$dumpall
$end
#0
$dumpvars
bx #"
bx ""
bx !"
bx ~
bx }
bx |
bx {
bx z
bx y
bx x
bx w
bx v
bx u
bx t
bx s
bx r
xq
xp
xo
xn
xm
xl
xk
1j
0i
bx h
b10000000000000000000000000000011 g
b1 f
b1 e
1d
0c
0b
xa
x`
x_
x^
x]
x\
x[
xZ
xY
xX
xW
xV
xU
xT
xS
xR
xQ
xP
xO
xN
xM
xL
xK
xJ
xI
xH
xG
xF
xE
xD
xC
xB
xA
x@
x?
x>
x=
x<
x;
x:
x9
x8
x7
x6
x5
x4
x3
x2
x1
x0
x/
x.
x-
x,
x+
x*
x)
x(
x'
x&
x%
x$
x#
x"
x!
$end
#1000
b10 f
#3000
bx1 {
1c
#5000
0c
#7000
bx11 {
1c
#9000
0c
#11000
bx111 {
1c
#13000
0c
#15000
bx1111 {
1c
#17000
0c
#19000
bx11111 {
1c
#21000
0c
#23000
bx111111 {
1c
#25000
0c
#27000
bx1111111 {
1c
#29000
0c
#31000
1m
b11111111 {
1c
#33000
0c
#35000
bx1 }
1c
#37000
0c
#39000
bx11 }
1c
#41000
0c
#43000
bx111 }
1c
#45000
0c
#47000
bx1111 }
1c
#49000
0c
#51000
bx11111 }
1c
#53000
0c
#55000
bx111111 }
1c
#57000
0c
#59000
bx1111111 }
1c
#61000
0c
#63000
1l
b11111111 }
1c
#65000
0c
#67000
bx1 !"
1c
#69000
0c
#71000
bx11 !"
1c
#73000
0c
#75000
bx111 !"
1c
#77000
0c
#79000
bx1111 !"
1c
#81000
0c
#83000
bx11111 !"
1c
#85000
0c
#87000
bx111111 !"
1c
#89000
0c
#91000
bx1111111 !"
1c
#93000
0c
#95000
1k
b11111111 !"
1c
#97000
0c
#99000
bx1 #"
1c
#101000
0c
#103000
bx11 #"
1c
#105000
0c
#107000
bx111 #"
1c
#109000
0c
#111000
bx1111 #"
1c
#113000
0c
#115000
bx11111 #"
1c
#117000
0c
#119000
bx111111 #"
1c
#121000
0c
#123000
bx1111111 #"
1c
#125000
0c
#127000
1p
b11111111 #"
1c
#129000
0c
#131000
bx1 s
1c
#133000
0c
#135000
bx11 s
1c
#137000
0c
#139000
bx111 s
1c
#141000
0c
#143000
bx1111 s
1c
#145000
0c
#147000
bx11111 s
1c
#149000
0c
#151000
bx111111 s
1c
#153000
0c
#155000
bx1111111 s
1c
#157000
0c
#159000
1q
b11111111 s
1c
#161000
0c
#163000
bx1 u
1c
#165000
0c
#167000
bx11 u
1c
#169000
0c
#171000
bx111 u
1c
#173000
0c
#175000
bx1111 u
1c
#177000
0c
#179000
bx11111 u
1c
#181000
0c
#183000
bx111111 u
1c
#185000
0c
#187000
bx1111111 u
1c
#189000
0c
#191000
1o
b11111111 u
1c
#193000
0c
#195000
bx1 w
1c
#197000
0c
#199000
bx11 w
1c
#201000
0c
#203000
bx111 w
1c
#205000
0c
#207000
bx1111 w
1c
#209000
0c
#211000
bx11111 w
1c
#213000
0c
#215000
bx111111 w
1c
#217000
0c
#219000
bx1111111 w
1c
#221000
0c
#223000
1n
b11111111 w
1c
#225000
0c
#227000
bx1 y
1c
#229000
0c
#231000
bx11 y
1c
#233000
0c
#235000
bx111 y
1c
#237000
0c
#239000
bx1111 y
1c
#241000
0c
#243000
bx11111 y
1c
#245000
0c
#247000
bx111111 y
1c
#249000
0c
#251000
bx1111111 y
1c
#253000
0c
#255000
1!
b11111111 y
1c
#259000
11
1?
1M
1[
15
1C
1Q
1_
14
1B
1P
1^
1-
1;
1I
1W
1,
1:
1H
1V
10
1>
1L
1Z
1"
1$
1&
1(
1*
18
1F
1T
13
1A
1O
1]
17
1E
1S
1a
16
1D
1R
1`
1/
1=
1K
1Y
1.
1<
1J
1X
12
1@
1N
1\
1#
1%
1'
1)
1+
19
1G
1U
b11111111 r
b11111111 t
b11111111 v
b11111111 x
b11111111 z
b11111111 |
b11111111 ~
b11111111 ""
1b
#261000
0b
#263000
b11111111111111111111111111111111 h
b11111111111111111111111111111111 e
